{
  "roommates": [
    {
      "id": "18366fd1",
      "nombre": "Isaac Kelley",
      "email": "isaac.kelley@example.com",
      "debe": 0,
      "recibe": 0
    },
    {
      "id": "bc943ed4",
      "nombre": "Stepan Kiriienko",
      "email": "stepan.kiriienko@example.com",
      "debe": 0,
      "recibe": 0
    },
    {
      "id": "27dde806",
      "nombre": "Enrique Gamboa",
      "email": "enrique.gamboa@example.com",
      "debe": 0,
      "recibe": 0
    },
    {
      "id": "df87dcac",
      "nombre": "Tilde Mortensen",
      "email": "tilde.mortensen@example.com",
      "debe": 0,
      "recibe": 0
    },
    {
      "id": "12f9a9fc",
      "nombre": "Luke Washington",
      "email": "luke.washington@example.com",
      "debe": 0,
      "recibe": 0
    }
  ]
}
